LICENSE
MANIFEST.in
README.rst
setup.py
speed_test.py
test_blist.py
blist/__init__.py
blist/_blist.c
blist/_btuple.py
blist/_sorteddict.py
blist/_sortedlist.py
blist/blist.h
blist.egg-info/PKG-INFO
blist.egg-info/SOURCES.txt
blist.egg-info/dependency_links.txt
blist.egg-info/not-zip-safe
blist.egg-info/top_level.txt
blist/test/__init__.py
blist/test/btuple_tests.py
blist/test/list_tests.py
blist/test/mapping_tests.py
blist/test/seq_tests.py
blist/test/sorteddict_tests.py
blist/test/sortedlist_tests.py
blist/test/test_list.py
blist/test/test_set.py
blist/test/test_support.py
blist/test/unittest.py
prototype/blist.py