Metadata-Version: 1.1
Name: blist
Version: 1.3.5
Summary: a list-like type with better asymptotic performance and similar performance on small lists
Home-page: http://stutzbachenterprises.com/blist/
Author: Stutzbach Enterprises, LLC
Author-email: daniel@stutzbachenterprises.com
License: BSD
Keywords: blist list b+tree btree fast copy-on-write sparse array sortedlist sorted sortedset weak weaksortedlist weaksortedset sorteddict btuple
Platform: UNKNOWN
Classifier: Development Status :: 5 - Production/Stable
Classifier: Intended Audience :: Developers
Classifier: Intended Audience :: Science/Research
Classifier: License :: OSI Approved :: BSD License
Classifier: Programming Language :: C
Classifier: Programming Language :: Python :: 2.5
Classifier: Programming Language :: Python :: 2.6
Classifier: Programming Language :: Python :: 2.7
Classifier: Programming Language :: Python :: 3
Classifier: Programming Language :: Python :: 3.1
Classifier: Programming Language :: Python :: 3.2
Provides: blist
